essay/__init__.py
essay/log.py
essay/main.py
essay/pip_.py
essay/project.py
essay/settings.py
essay/utils.py
essay/tasks/__init__.py
essay/tasks/build.py
essay/tasks/config.py
essay/tasks/deploy.py
essay/tasks/fs.py
essay/tasks/git.py
essay/tasks/nginx.py
essay/tasks/package.py
essay/tasks/process.py
essay/tasks/pypi.py
essay/tasks/supervisor.py
essay/tasks/util.py
essay/tasks/validate.py
essay/tasks/virtualenv.py
essay/templates/default/MANIFEST.in.tpl
essay/templates/default/README.tpl
essay/templates/default/setup.py.tpl
essay/templates/default/__project__/__init__.py.tpl
essay/templates/default/__project__/log.py.tpl
essay/templates/default/__project__/main.py.tpl
essay/templates/default/__project__/settings.py.tpl
essay/templates/default/conf/supervisord.conf.tpl
essay/templates/default/fabfile/__init__.py.tpl
essay/templates/django/MANIFEST.in.tpl
essay/templates/django/README.tpl
essay/templates/django/setup.py.tpl
essay/templates/django/__project__/__init__.py.tpl
essay/templates/django/__project__/manage.py.tpl
essay/templates/django/__project__/__project__/__init__.py.tpl
essay/templates/django/__project__/__project__/settings.py.tpl
essay/templates/django/__project__/__project__/urls.py.tpl
essay/templates/django/__project__/__project__/wsgi.py.tpl
essay/templates/django/conf/supervisord.conf.tpl
essay/templates/django/fabfile/__init__.py.tpl
essay/templates/init/MANIFEST.in.tpl
essay/templates/init/README.tpl
essay/templates/init/setup.py.tpl
essay/templates/init/conf/supervisord.conf.tpl
essay/templates/init/fabfile/__init__.py.tpl
essay-0.0.8.dist-info/METADATA
essay-0.0.8.dist-info/RECORD
essay-0.0.8.dist-info/WHEEL
essay-0.0.8.dist-info/entry_points.txt
essay-0.0.8.dist-info/top_level.txt
